dataset_down/__init__.py
dataset_down/cli.py
dataset_down/api/AuthApi.py
dataset_down/api/__init__.py
dataset_down/client/AuthClient.py
dataset_down/client/__init__.py
dataset_down/config/__init__.py
dataset_down/config/constants.py
dataset_down/config/login_config.py
dataset_down/config/path_config.py
dataset_down/downloader/__init__.py
dataset_down/downloader/downloader.py
dataset_down/update/__init__.py
dataset_down/update/sdk_version.py
dataset_down/update/update_check.py
dataset_down/utils/__init__.py
dataset_down/utils/file.py
dataset_down/utils/http_utils.py
dataset_down/utils/retryable.py
dataset_down/utils/system_utils.py
dataset_down/utils/time_utils.py
dataset_down-0.1.0.dist-info/METADATA
dataset_down-0.1.0.dist-info/WHEEL
dataset_down-0.1.0.dist-info/entry_points.txt
dataset_down-0.1.0.dist-info/top_level.txt
dataset_down-0.1.0.dist-info/RECORD
